setup.py
Pro_video_tools.egg-info/PKG-INFO
Pro_video_tools.egg-info/SOURCES.txt
Pro_video_tools.egg-info/dependency_links.txt
Pro_video_tools.egg-info/top_level.txt
processamento/__init__.py
processamento/camera.py
processamento/video.py