Metadata-Version: 1.0
Name: Pro-video-tools
Version: 1.1
Summary: Este pacote te permite fazer operações em videos e camera
Home-page: UNKNOWN
Author: jhonatan de souza
Author-email: jhonatantools@gmail.com
License: UNKNOWN
Keywords: video,camera
Platform: UNKNOWN
